CHANGELOG.md
MANIFEST.in
README.md
setup.py
rookieninja/__init__.py
rookieninja/server.py
rookieninja/settings.py
rookieninja.egg-info/PKG-INFO
rookieninja.egg-info/SOURCES.txt
rookieninja.egg-info/dependency_links.txt
rookieninja.egg-info/entry_points.txt
rookieninja.egg-info/not-zip-safe
rookieninja.egg-info/requires.txt
rookieninja.egg-info/top_level.txt
rookieninja/models/__init__.py
rookieninja/models/fleet.py
rookieninja/models/index.py
rookieninja/modules/__init__.py
rookieninja/modules/db.py
rookieninja/modules/draw.py
rookieninja/modules/utils.py
rookieninja/routines/__init__.py
rookieninja/routines/clean_ram.py
rookieninja/routines/stats.py
rookieninja/static/base.css
rookieninja/static/robots.txt
rookieninja/static/imgs/Eve_Solarsystemname.png
rookieninja/static/imgs/add.png
rookieninja/static/imgs/class.png
rookieninja/static/imgs/constellation.png
rookieninja/static/imgs/dscan.png
rookieninja/static/imgs/effect.png
rookieninja/static/imgs/location.png
rookieninja/static/imgs/moon.png
rookieninja/static/imgs/name.png
rookieninja/static/imgs/planet.png
rookieninja/static/imgs/region.png
rookieninja/static/imgs/screenshot.png
rookieninja/static/imgs/screenshot_original.png
rookieninja/static/imgs/ship.png
rookieninja/static/imgs/star.png
rookieninja/static/imgs/static.png
rookieninja/static/imgs/wh.png
rookieninja/templates/fleet.tpl
rookieninja/templates/index.tpl
rookieninja/views/__init__.py
rookieninja/views/fleet.py
rookieninja/views/index.py